COPYING
MANIFEST.in
coverage.ini
setup.py
tox.ini
unittest.cfg
src/mailman_pgp/__init__.py
src/mailman_pgp/plugin.py
src/mailman_pgp.egg-info/PKG-INFO
src/mailman_pgp.egg-info/SOURCES.txt
src/mailman_pgp.egg-info/dependency_links.txt
src/mailman_pgp.egg-info/not-zip-safe
src/mailman_pgp.egg-info/requires.txt
src/mailman_pgp.egg-info/top_level.txt
src/mailman_pgp/archivers/__init__.py
src/mailman_pgp/archivers/local_maildir.py
src/mailman_pgp/archivers/local_mbox.py
src/mailman_pgp/archivers/remote.py
src/mailman_pgp/archivers/tests/__init__.py
src/mailman_pgp/archivers/tests/test_maildir.py
src/mailman_pgp/archivers/tests/test_mbox.py
src/mailman_pgp/chains/__init__.py
src/mailman_pgp/chains/default.py
src/mailman_pgp/chains/moderation.py
src/mailman_pgp/chains/tests/__init__.py
src/mailman_pgp/chains/tests/test_default.py
src/mailman_pgp/commands/__init__.py
src/mailman_pgp/commands/eml_key.py
src/mailman_pgp/commands/tests/__init__.py
src/mailman_pgp/commands/tests/test_key.py
src/mailman_pgp/config/__init__.py
src/mailman_pgp/config/config.py
src/mailman_pgp/config/converter.py
src/mailman_pgp/config/mailman.cfg
src/mailman_pgp/config/mailman_pgp.cfg
src/mailman_pgp/config/schema.cfg
src/mailman_pgp/config/validator.py
src/mailman_pgp/config/tests/__init__.py
src/mailman_pgp/config/tests/test_config.py
src/mailman_pgp/config/tests/test_converter.py
src/mailman_pgp/config/tests/test_validator.py
src/mailman_pgp/database/__init__.py
src/mailman_pgp/database/types.py
src/mailman_pgp/handlers/__init__.py
src/mailman_pgp/handlers/signature_strip.py
src/mailman_pgp/handlers/tests/__init__.py
src/mailman_pgp/handlers/tests/test_signature_strip.py
src/mailman_pgp/model/__init__.py
src/mailman_pgp/model/address.py
src/mailman_pgp/model/base.py
src/mailman_pgp/model/db_key.py
src/mailman_pgp/model/fs_key.py
src/mailman_pgp/model/list.py
src/mailman_pgp/model/sighash.py
src/mailman_pgp/model/tests/__init__.py
src/mailman_pgp/model/tests/test_db_key.py
src/mailman_pgp/model/tests/test_fs_key.py
src/mailman_pgp/model/tests/test_list.py
src/mailman_pgp/mta/__init__.py
src/mailman_pgp/mta/bulk.py
src/mailman_pgp/mta/deliver.py
src/mailman_pgp/mta/personalized.py
src/mailman_pgp/mta/tests/__init__.py
